{
  "n_subjects_processed": 20,
  "n_subjects_total": 20,
  "output_directory": "brainweb_subjects",
  "subjects": [
    {
      "subject_idx": 0,
      "subject_name": "subject_00",
      "slice_shape": [
        434,
        362
      ],
      "3layer": {
        "unique_labels": [
          0,
          1,
          2,
          3
        ],
        "background_pixels": 46315,
        "tissue_pixels": 110793
      },
      "6layer": {
        "unique_labels": [
          0,
          1,
          2,
          3,
          4,
          5,
          6
        ],
        "background_pixels": 46315,
        "tissue_pixels": 110793
      },
      "9layer": {
        "unique_labels": [
          0,
          1,
          2,
          3,
          4,
          5,
          6,
          7,
          8,
          9
        ],
        "background_pixels": 46315,
        "tissue_pixels": 110793
      }
    },
    {
      "subject_idx": 1,
      "subject_name": "subject_01",
      "slice_shape": [
        434,
        362
      ],
      "3layer": {
        "unique_labels": [
          0,
          1,
          2,
          3
        ],
        "background_pixels": 53090,
        "tissue_pixels": 104018
      },
      "6layer": {
        "unique_labels": [
          0,
          1,
          2,
          3,
          4,
          5,
          6
        ],
        "background_pixels": 53090,
        "tissue_pixels": 104018
      },
      "9layer": {
        "unique_labels": [
          0,
          1,
          2,
          3,
          4,
          5,
          6,
          7,
          8,
          9
        ],
        "background_pixels": 53090,
        "tissue_pixels": 104018
      }
    },
    {
      "subject_idx": 2,
      "subject_name": "subject_02",
      "slice_shape": [
        434,
        362
      ],
      "3layer": {
        "unique_labels": [
          0,
          1,
          2,
          3
        ],
        "background_pixels": 39570,
        "tissue_pixels": 117538
      },
      "6layer": {
        "unique_labels": [
          0,
          1,
          2,
          3,
          4,
          5,
          6
        ],
        "background_pixels": 39570,
        "tissue_pixels": 117538
      },
      "9layer": {
        "unique_labels": [
          0,
          1,
          2,
          3,
          4,
          5,
          6,
          7,
          8,
          9
        ],
        "background_pixels": 39570,
        "tissue_pixels": 117538
      }
    },
    {
      "subject_idx": 3,
      "subject_name": "subject_03",
      "slice_shape": [
        434,
        362
      ],
      "3layer": {
        "unique_labels": [
          0,
          1,
          2,
          3
        ],
        "background_pixels": 45308,
        "tissue_pixels": 111800
      },
      "6layer": {
        "unique_labels": [
          0,
          1,
          2,
          3,
          4,
          5,
          6
        ],
        "background_pixels": 45308,
        "tissue_pixels": 111800
      },
      "9layer": {
        "unique_labels": [
          0,
          1,
          2,
          3,
          4,
          5,
          6,
          7,
          8,
          9
        ],
        "background_pixels": 45308,
        "tissue_pixels": 111800
      }
    },
    {
      "subject_idx": 4,
      "subject_name": "subject_04",
      "slice_shape": [
        434,
        362
      ],
      "3layer": {
        "unique_labels": [
          0,
          1,
          2,
          3
        ],
        "background_pixels": 52775,
        "tissue_pixels": 104333
      },
      "6layer": {
        "unique_labels": [
          0,
          1,
          2,
          3,
          4,
          5,
          6
        ],
        "background_pixels": 52775,
        "tissue_pixels": 104333
      },
      "9layer": {
        "unique_labels": [
          0,
          1,
          2,
          3,
          4,
          5,
          6,
          7,
          8,
          9
        ],
        "background_pixels": 52775,
        "tissue_pixels": 104333
      }
    },
    {
      "subject_idx": 5,
      "subject_name": "subject_05",
      "slice_shape": [
        434,
        362
      ],
      "3layer": {
        "unique_labels": [
          0,
          1,
          2,
          3
        ],
        "background_pixels": 46439,
        "tissue_pixels": 110669
      },
      "6layer": {
        "unique_labels": [
          0,
          1,
          2,
          3,
          4,
          5,
          6
        ],
        "background_pixels": 46439,
        "tissue_pixels": 110669
      },
      "9layer": {
        "unique_labels": [
          0,
          1,
          2,
          3,
          4,
          5,
          6,
          7,
          8,
          9
        ],
        "background_pixels": 46439,
        "tissue_pixels": 110669
      }
    },
    {
      "subject_idx": 6,
      "subject_name": "subject_06",
      "slice_shape": [
        434,
        362
      ],
      "3layer": {
        "unique_labels": [
          0,
          1,
          2,
          3
        ],
        "background_pixels": 48151,
        "tissue_pixels": 108957
      },
      "6layer": {
        "unique_labels": [
          0,
          1,
          2,
          3,
          4,
          5,
          6
        ],
        "background_pixels": 48947,
        "tissue_pixels": 108161
      },
      "9layer": {
        "unique_labels": [
          0,
          1,
          2,
          3,
          4,
          5,
          6,
          7,
          8,
          9
        ],
        "background_pixels": 48151,
        "tissue_pixels": 108957
      }
    },
    {
      "subject_idx": 7,
      "subject_name": "subject_07",
      "slice_shape": [
        434,
        362
      ],
      "3layer": {
        "unique_labels": [
          0,
          1,
          2,
          3
        ],
        "background_pixels": 49583,
        "tissue_pixels": 107525
      },
      "6layer": {
        "unique_labels": [
          0,
          1,
          2,
          3,
          4,
          5,
          6
        ],
        "background_pixels": 49583,
        "tissue_pixels": 107525
      },
      "9layer": {
        "unique_labels": [
          0,
          1,
          2,
          3,
          4,
          5,
          6,
          7,
          8,
          9
        ],
        "background_pixels": 49583,
        "tissue_pixels": 107525
      }
    },
    {
      "subject_idx": 8,
      "subject_name": "subject_08",
      "slice_shape": [
        434,
        362
      ],
      "3layer": {
        "unique_labels": [
          0,
          1,
          2,
          3
        ],
        "background_pixels": 48743,
        "tissue_pixels": 108365
      },
      "6layer": {
        "unique_labels": [
          0,
          1,
          2,
          3,
          4,
          5,
          6
        ],
        "background_pixels": 48743,
        "tissue_pixels": 108365
      },
      "9layer": {
        "unique_labels": [
          0,
          1,
          2,
          3,
          4,
          5,
          6,
          7,
          8,
          9
        ],
        "background_pixels": 48743,
        "tissue_pixels": 108365
      }
    },
    {
      "subject_idx": 9,
      "subject_name": "subject_09",
      "slice_shape": [
        434,
        362
      ],
      "3layer": {
        "unique_labels": [
          0,
          1,
          2,
          3
        ],
        "background_pixels": 48378,
        "tissue_pixels": 108730
      },
      "6layer": {
        "unique_labels": [
          0,
          1,
          2,
          3,
          4,
          5,
          6
        ],
        "background_pixels": 48378,
        "tissue_pixels": 108730
      },
      "9layer": {
        "unique_labels": [
          0,
          1,
          2,
          3,
          4,
          5,
          6,
          7,
          8,
          9
        ],
        "background_pixels": 48378,
        "tissue_pixels": 108730
      }
    },
    {
      "subject_idx": 10,
      "subject_name": "subject_10",
      "slice_shape": [
        434,
        362
      ],
      "3layer": {
        "unique_labels": [
          0,
          1,
          2,
          3
        ],
        "background_pixels": 49543,
        "tissue_pixels": 107565
      },
      "6layer": {
        "unique_labels": [
          0,
          1,
          2,
          3,
          4,
          5,
          6
        ],
        "background_pixels": 49543,
        "tissue_pixels": 107565
      },
      "9layer": {
        "unique_labels": [
          0,
          1,
          2,
          3,
          4,
          5,
          6,
          7,
          8,
          9
        ],
        "background_pixels": 49543,
        "tissue_pixels": 107565
      }
    },
    {
      "subject_idx": 11,
      "subject_name": "subject_11",
      "slice_shape": [
        434,
        362
      ],
      "3layer": {
        "unique_labels": [
          0,
          1,
          2,
          3
        ],
        "background_pixels": 44861,
        "tissue_pixels": 112247
      },
      "6layer": {
        "unique_labels": [
          0,
          1,
          2,
          3,
          4,
          5,
          6
        ],
        "background_pixels": 44861,
        "tissue_pixels": 112247
      },
      "9layer": {
        "unique_labels": [
          0,
          1,
          2,
          3,
          4,
          5,
          6,
          7,
          8,
          9
        ],
        "background_pixels": 44861,
        "tissue_pixels": 112247
      }
    },
    {
      "subject_idx": 12,
      "subject_name": "subject_12",
      "slice_shape": [
        434,
        362
      ],
      "3layer": {
        "unique_labels": [
          0,
          1,
          2,
          3
        ],
        "background_pixels": 45297,
        "tissue_pixels": 111811
      },
      "6layer": {
        "unique_labels": [
          0,
          1,
          2,
          3,
          4,
          5,
          6
        ],
        "background_pixels": 45297,
        "tissue_pixels": 111811
      },
      "9layer": {
        "unique_labels": [
          0,
          1,
          2,
          3,
          4,
          5,
          6,
          7,
          8,
          9
        ],
        "background_pixels": 45297,
        "tissue_pixels": 111811
      }
    },
    {
      "subject_idx": 13,
      "subject_name": "subject_13",
      "slice_shape": [
        434,
        362
      ],
      "3layer": {
        "unique_labels": [
          0,
          1,
          2,
          3
        ],
        "background_pixels": 44309,
        "tissue_pixels": 112799
      },
      "6layer": {
        "unique_labels": [
          0,
          1,
          2,
          3,
          4,
          5,
          6
        ],
        "background_pixels": 44309,
        "tissue_pixels": 112799
      },
      "9layer": {
        "unique_labels": [
          0,
          1,
          2,
          3,
          4,
          5,
          6,
          7,
          8,
          9
        ],
        "background_pixels": 44309,
        "tissue_pixels": 112799
      }
    },
    {
      "subject_idx": 14,
      "subject_name": "subject_14",
      "slice_shape": [
        434,
        362
      ],
      "3layer": {
        "unique_labels": [
          0,
          1,
          2,
          3
        ],
        "background_pixels": 45344,
        "tissue_pixels": 111764
      },
      "6layer": {
        "unique_labels": [
          0,
          1,
          2,
          3,
          4,
          5,
          6
        ],
        "background_pixels": 45344,
        "tissue_pixels": 111764
      },
      "9layer": {
        "unique_labels": [
          0,
          1,
          2,
          3,
          4,
          5,
          6,
          7,
          8,
          9
        ],
        "background_pixels": 45344,
        "tissue_pixels": 111764
      }
    },
    {
      "subject_idx": 15,
      "subject_name": "subject_15",
      "slice_shape": [
        434,
        362
      ],
      "3layer": {
        "unique_labels": [
          0,
          1,
          2,
          3
        ],
        "background_pixels": 48052,
        "tissue_pixels": 109056
      },
      "6layer": {
        "unique_labels": [
          0,
          1,
          2,
          3,
          4,
          5,
          6
        ],
        "background_pixels": 48052,
        "tissue_pixels": 109056
      },
      "9layer": {
        "unique_labels": [
          0,
          1,
          2,
          3,
          4,
          5,
          6,
          7,
          8,
          9
        ],
        "background_pixels": 48052,
        "tissue_pixels": 109056
      }
    },
    {
      "subject_idx": 16,
      "subject_name": "subject_16",
      "slice_shape": [
        434,
        362
      ],
      "3layer": {
        "unique_labels": [
          0,
          1,
          2,
          3
        ],
        "background_pixels": 51311,
        "tissue_pixels": 105797
      },
      "6layer": {
        "unique_labels": [
          0,
          1,
          2,
          3,
          4,
          5,
          6
        ],
        "background_pixels": 51311,
        "tissue_pixels": 105797
      },
      "9layer": {
        "unique_labels": [
          0,
          1,
          2,
          3,
          4,
          5,
          6,
          7,
          8,
          9
        ],
        "background_pixels": 51311,
        "tissue_pixels": 105797
      }
    },
    {
      "subject_idx": 17,
      "subject_name": "subject_17",
      "slice_shape": [
        434,
        362
      ],
      "3layer": {
        "unique_labels": [
          0,
          1,
          2,
          3
        ],
        "background_pixels": 52731,
        "tissue_pixels": 104377
      },
      "6layer": {
        "unique_labels": [
          0,
          1,
          2,
          3,
          4,
          5,
          6
        ],
        "background_pixels": 52731,
        "tissue_pixels": 104377
      },
      "9layer": {
        "unique_labels": [
          0,
          1,
          2,
          3,
          4,
          5,
          6,
          7,
          8,
          9
        ],
        "background_pixels": 52731,
        "tissue_pixels": 104377
      }
    },
    {
      "subject_idx": 18,
      "subject_name": "subject_18",
      "slice_shape": [
        434,
        362
      ],
      "3layer": {
        "unique_labels": [
          0,
          1,
          2,
          3
        ],
        "background_pixels": 48342,
        "tissue_pixels": 108766
      },
      "6layer": {
        "unique_labels": [
          0,
          1,
          2,
          3,
          4,
          5,
          6
        ],
        "background_pixels": 48342,
        "tissue_pixels": 108766
      },
      "9layer": {
        "unique_labels": [
          0,
          1,
          2,
          3,
          4,
          5,
          6,
          7,
          8,
          9
        ],
        "background_pixels": 48342,
        "tissue_pixels": 108766
      }
    },
    {
      "subject_idx": 19,
      "subject_name": "subject_19",
      "slice_shape": [
        434,
        362
      ],
      "3layer": {
        "unique_labels": [
          0,
          1,
          2,
          3
        ],
        "background_pixels": 44286,
        "tissue_pixels": 112822
      },
      "6layer": {
        "unique_labels": [
          0,
          1,
          2,
          3,
          4,
          5,
          6
        ],
        "background_pixels": 44286,
        "tissue_pixels": 112822
      },
      "9layer": {
        "unique_labels": [
          0,
          1,
          2,
          3,
          4,
          5,
          6,
          7,
          8,
          9
        ],
        "background_pixels": 44286,
        "tissue_pixels": 112822
      }
    }
  ]
}